{"Авиационно-космическое агентство": "102000254", "Агентство международного сотрудничества и развития": "102000092", "Агентство по боеприпасам": "102000233", "Агентство по обычным вооружениям": "102000234", "Агентство по патентам и товарным знакам": "102000093", "Агентство по правовой охране программ для ЭВМ, баз данных и топологий интегральных микросхем": "102000094", "Администрация": "102000095", "Администрация Особой экономической зоны в Калининградской области": "102000342", "Администрация Президента": "102000040", "Ассоциация волонтерских центров": "603115957", "Ассоциация крестьянских (фермерских) хозяйств и сельскохозяйственных кооперативов России": "102000350", "Верховный Совет": "102000041", "Верховный Суд": "102000096", "Вице-президент": "102000042", "Всероссийский центральный исполнительный комитет": "102000043", "Всесоюзный Центральный Совет Профессиональных Союзов": "102000091", "Высший Арбитражный Суд": "102000097", "Генеральная прокуратура": "102000304", "Генеральный прокурор": "102000098", "Глава": "102000347", "Главное государственно-правовое управление Президента": "102000044", "Главное управление специальных программ Президента": "102000236", "Главный государственный ветеринарный инспектор": "102000099", "Главный государственный санитарный врач": "102000237", "Госкомимущество": "102000305", "Госкомсевер": "102000314", "Госнаркоконтроль России": "102000320", "Госстрой": "102000315", "Государственная архивная служба": "102000100", "Государственная Дума Федерального Собрания": "102000045", "Государственная инспекция по обеспечению государственной монополии на алкогольную продукцию при Правительстве": "102000306", "Государственная корпорация по атомной энергии \"Росатом\"": "102000353", "Государственная корпорация по космической деятельности \"Роскосмос\"": "102411525", "Государственная налоговая служба": "102000102", "Государственная техническая комиссия при Президенте": "102000103", "Государственная фельдъегерская служба": "102000104", "Государственная фельдъегерская служба при Правительстве": "102000316", "Государственная хлебная инспекция при Правительстве": "102000255", "Государственно-правовое управление Президента": "102000046", "Государственный антимонопольный комитет": "102000307", "Государственный земельный комитет": "102000105", "Государственный комитет по антимонопольной политике и поддержке новых экономических структур": "102000106", "Государственный комитет по военно-технической политике": "102000107", "Государственный комитет по вопросам архитектуры и строительства": "102000108", "Государственный комитет по вопросам развития Севера": "102000109", "Государственный комитет по высшему образованию": "102000110", "Государственный комитет по делам гражданской обороны, чрезвычайным ситуациям и ликвидации последствий стихийных бедствий": "102000111", "Государственный комитет по делам Севера": "102000238", "Государственный комитет по земельным ресурсам и землеустройству": "102000112", "Государственный комитет по кинематографии": "102000113", "Государственный комитет по контролю за оборотом наркотических средств и психотропных веществ": "102000260", "Государственный комитет по охране окружающей среды": "102000114", "Государственный комитет по патентам и товарным знакам": "102000308", "Государственный комитет по рыболовству": "102000115", "Государственный комитет по связи и информатизации": "102000116", "Государственный комитет по социальной защите граждан и реабилитации территорий, пострадавших от чернобыльской и других радиационных катастроф": "102000117", "Государственный комитет по стандартизации и метрологии": "102000119", "Государственный комитет по стандартизации, метрологии и сертификации": "102000118", "Государственный комитет по статистике": "102000120", "Государственный комитет по строительной, архитектурной и жилищной политике": "102000239", "Государственный комитет по строительству и жилищно-коммунальному комплексу": "102000121", "Государственный комитет по телекоммуникациям": "102000240", "Государственный комитет по управлению государственным имуществом": "102000122", "Государственный комитет по физической культуре и спорту": "102000261", "Государственный комитет по физической культуре и туризму": "102000123", "Государственный комитет Российской Федерации по контролю за оборотом наркотических средств и психотропных веществ": "102000375", "Государственный комитет санитарно-эпидемиологического надзора": "102000124", "Государственный секретарь": "102000047", "Государственный секретарь - Первый заместитель Председателя Правительства": "102000048", "Государственный страховой надзор": "102000125", "Государственный таможенный комитет": "102000126", "Губернатор": "102000364", "Департамент налоговой полиции": "102000127", "Дорожное агентство": "102000241", "Заместитель Председателя Верховного Совета": "102000051", "Заместитель Председателя Правительства": "102000052", "Заместитель Председателя Совета Министров - Правительства": "102000053", "Исполняющий обязанности Президента": "102000054", "Кабинет Министров": "102000055", "Комитет по водному хозяйству": "102000309", "Комитет по военно-техническому сотрудничеству с иностранными государствами": "102000129", "Комитет по геологии и использованию недр": "102000130", "Комитет по делам архивов": "102000131", "Комитет по драгоценным металлам и драгоценным камням": "102000132", "Комитет по земельной реформе и земельным ресурсам": "102000133", "Комитет по земельным ресурсам и землеустройству": "102000134", "Комитет по кинематографии": "102000135", "Комитет по металлургии": "102000136", "Комитет по оперативному управлению народным хозяйством": "102000056", "Комитет по патентам и товарным знакам": "102000137", "Комитет по политике цен": "102000138", "Комитет по рыболовству": "102000139", "Комитет по социально-экономическому развитию Севера": "102000140", "Комитет по стандартизации, метрологии и сертификации": "102000141", "Комитет по торговле": "102000142", "Комитет по туризму": "102000143", "Комитет по финансовому мониторингу": "102000262", "Конституционный Суд": "102000057", "Межгосударственный экономический комитет": "102000058", "Межреспубликанский экономический комитет": "102000059", "Мининистерство науки и технологий": "102000310", "Министерство архитектуры, строительства и жилищно-коммунального хозяйства": "102000145", "Министерство безопасности": "102000146", "Министерство внешних экономических связей": "102000147", "Министерство внешних экономических связей и торговли": "102000148", "Министерство внутренних дел": "102000149", "Министерство государственного имущества": "102000150", "Министерство здравоохранения": "102000151", "Министерство здравоохранения и медицинской промышленности": "102000152", "Министерство здравоохранения и социального развития": "102000153", "Министерство имущественных отношений": "102000242", "Министерство иностранных дел": "102000154", "Министерство информационных технологий и связи": "102000269", "Министерство культуры": "102000155", "Министерство культуры и массовых коммуникаций": "102000243", "Министерство культуры и туризма": "102000311", "Министерство науки и высшего образования": "102479504", "Министерство науки и технической политики": "102000157", "Министерство науки и технологий": "102000158", "Министерство науки, высшей школы и технической политики": "102000156", "Министерство обороны": "102000159", "Министерство образования": "102000160", "Министерство образования и науки": "102000244", "Министерство общего и профессионального образования": "102000161", "Министерство охраны окружающей среды и природных ресурсов": "102000162", "Министерство печати и информации": "102000163", "Министерство по антимонопольной политике и поддержке предпринимательства": "102000164", "Министерство по атомной энергии": "102000165", "Министерство по внешним экономическим связям": "102000166", "Министерство по делам гражданской обороны, чрезвычайным ситуациям и ликвидации последствий стихийных бедствий": "102000167", "Министерство по делам национальностей и региональной политике": "102000168", "Министерство по делам печати, телерадиовещания и средств массовых коммуникаций": "102000245", "Министерство по делам федерации, национальной и миграционной политики": "102000169", "Министерство по земельной политике, строительству и жилищно-коммунальному хозяйству": "102000170", "Министерство по налогам и сборам": "102000171", "Министерство по связи и информатизации": "102000172", "Министерство по сотрудничеству с государствами - участниками Содружества Независимых Государств": "102000173", "Министерство по физической культуре, спорту и туризму": "102000246", "Министерство природных ресурсов": "102000174", "Министерство природных ресурсов и экологии": "102000354", "Министерство промышленности и торговли": "102000358", "Министерство промышленности и энергетики": "102000176", "Министерство промышленности, науки и технологий": "102000175", "Министерство просвещения": "102483115", "Министерство путей сообщения": "102000177", "Министерство регионального развития": "102000282", "Министерство Российской Федерации по делам гражданской обороны, чрезвычайным ситуациям и ликвидации последствий стихийных бедствий": "102000372", "Министерство Российской Федерации по делам Крыма": "102372581", "Министерство Российской Федерации по делам Северного Кавказа": "102376971", "Министерство Российской Федерации по развитию Дальнего Востока": "102000380", "Министерство Российской Федерации по развитию Дальнего Востока и Арктики": "102552423", "Министерство связи": "102000178", "Министерство связи и массовых коммуникаций": "102000355", "Министерство сельского хозяйства": "102000179", "Министерство сельского хозяйства и продовольствия": "102000180", "Министерство социальной защиты населения": "102000181", "Министерство спорта": "102000377", "Министерство спорта, туризма и молодежной политики": "102000357", "Министерство строительства": "102000182", "Министерство строительства и жилищно-коммунального хозяйства": "102348522", "Министерство топлива и энергетики": "102000183", "Министерство торговли": "102000184", "Министерство транспорта": "102000185", "Министерство транспорта и связи": "102000256", "Министерство труда": "102000186", "Министерство труда и социального развития": "102000187", "Министерство труда и социальной защиты": "102000378", "Министерство финансов": "102000188", "Министерство цифрового развития, связи и массовых коммуникаций": "102472498", "Министерство экологии и природных ресурсов": "102000189", "Министерство экономики": "102000190", "Министерство экономики и финансов": "102000191", "Министерство экономического развития": "102000352", "Министерство экономического развития и торговли": "102000192", "Министерство энергетики": "102000193", "Министерство юстиции": "102000194", "Министр обороны": "102000365", "Минстрой": "102000312", "Начальник Государственно-правового управления Президента": "102000060", "Независимый профсоюз горняков России": "102000061", "Общероссийская общественная организация \"Паралимпийский комитет России\"": "102403961", "Общероссийская общественная организация \"Российский студенческий спортивный союз\"": "102596014", "Общероссийская общественно-государственная организация \"Добровольное общество содействия армии, авиации и флоту России\"": "102461704", "Общероссийский союз общественных объединений \"Олимпийский комитет России\"": "102000369", "Общероссийский союз физкультурно-спортивных общественных объединений инвалидов \"Сурдлимпийский комитет России\"": "102442003", "Открытое акционерное общество \"Газпром\"": "102000263", "Пенсионный фонд": "102000195", "Первый заместитель Председателя Верховного Совета": "102000062", "Первый Заместитель Председателя Правительства": "102000063", "Первый заместитель Председателя Совета Министров": "102000064", "Первый заместитель Председателя Совета Министров - Правительства": "102000065", "Правительство": "102000066", "Правление Министерства по антимонопольной политике и поддержке предпринимательства": "102000317", "Правление Пенсионного фонда": "102000264", "Председатель Верховного Совета": "102000067", "Председатель Совета Министров": "102000068", "Председатель Совета Министров - Правительства": "102000069", "Президент": "102000070", "Президиум Верховного Совета": "102000071", "Президиум Высшего аттестационного комитета": "102000196", "Профсоюз работников культуры": "102000318", "Российская академия медицинских наук": "102000257", "Российская академия наук": "102000313", "Российский независимый профсоюз работников угольной промышленности": "102000072", "Российское агентство по государственным резервам": "102000270", "Российское космическое агентство при Правительстве Российской Федерации": "102373124", "Российское общество Красного Креста": "102000319", "Руководитель комитета по оперативному управлению народным хозяйством": "102000073", "Сберегательный банк": "102000197", "Секретарь Совета безопасности": "102000074", "Следственный комитет": "102361460", "Служба внешней разведки": "102000198", "Служба специальной связи и информации при Федеральной службе охраны": "102000335", "Совет Министров": "102000076", "Совет Министров - Правительство": "102000077", "Совет Народных Комиссаров": "102000078", "Совет Национальностей Верховного Совета": "102000079", "Совет Республики Верховного Совета": "102000080", "Совет Федерации Независимых Профессиональных Союзов": "102000379", "Совет Федерации независимых профсоюзов": "102000081", "Совет Федерации Федерального Собрания": "102000082", "Счетная палата": "102403599", "Съезд народных депутатов": "102000083", "Управление делами Президента": "102000265", "Федеральная авиационная служба России": "102373309", "Федеральная антимонопольная служба": "102000201", "Федеральная архивная служба России": "102373310", "Федеральная аэронавигационная служба": "102000332", "Федеральная дорожная служба России": "102373311", "Федеральная комиссия по рынку ценных бумаг": "102000204", "Федеральная миграционная служба": "102000205", "Федеральная налоговая служба": "102000206", "Федеральная пограничная служба": "102000207", "Федеральная пробирная палата": "102838531", "Федеральная регистрационная служба": "102000283", "Федеральная служба безопасности": "102000208", "Федеральная служба воздушного транспорта России": "102373312", "Федеральная служба войск национальной гвардии": "102409146", "Федеральная служба геодезии и картографии": "102000210", "Федеральная служба государственной регистрации, кадастра и картографии": "102000368", "Федеральная служба государственной статистики": "102000296", "Федеральная служба железнодорожных войск": "102000247", "Федеральная служба занятости": "102000211", "Федеральная служба земельного кадастра": "102000212", "Федеральная служба исполнения наказаний": "102000284", "Федеральная служба контрразведки": "102000213", "Федеральная служба лесного хозяйства": "102000214", "Федеральная служба налоговой полиции": "102000215", "Федеральная служба охраны": "102000216", "Федеральная служба по аккредитации": "102000376", "Федеральная служба по валютному и экспортному контролю": "102000217", "Федеральная служба по ветеринарному и фитосанитарному надзору": "102000285", "Федеральная служба по военно-техническому сотрудничеству": "102000337", "Федеральная служба по гидрометеорологии и мониторингу окружающей среды": "102000248", "Федеральная служба по делам о несостоятельности и финансовому оздоровлению": "102000249", "Федеральная служба по интеллектуальной собственности": "102000371", "Федеральная служба по интеллектуальной собственности, патентам и товарным знакам": "102000360", "Федеральная служба по надзору в сфере защиты прав потребителей и благополучия человека": "102000271", "Федеральная служба по надзору в сфере здравоохранения": "102000381", "Федеральная служба по надзору в сфере здравоохранения и социального развития": "102000272", "Федеральная служба по надзору в сфере массовых коммуникаций, связи и охраны культурного наследия": "102000349", "Федеральная служба по надзору в сфере образования и науки": "102000297", "Федеральная служба по надзору в сфере природопользования": "102000302", "Федеральная служба по надзору в сфере связи": "102000324", "Федеральная служба по надзору в сфере связи, информационных технологий и массовых коммуникаций": "102000367", "Федеральная служба по надзору в сфере транспорта": "102000294", "Федеральная служба по надзору за соблюдением законодательства в области охраны культурного наследия": "102000361", "Федеральная служба по надзору за соблюдением законодательства в сфере массовых коммуникаций и охране культурного наследия": "102000326", "Федеральная служба по надзору за страховой деятельностью": "102000219", "Федеральная служба по обеспечению государственной монополии на алкогольную продукцию": "102000220", "Федеральная служба по оборонному заказу": "102000292", "Федеральная служба по регулированию алкогольного рынка": "102000366", "Федеральная служба по регулированию естественных монополий в области связи": "102000221", "Федеральная служба по регулированию естественных монополий на транспорте": "102000222", "Федеральная служба по тарифам": "102000223", "Федеральная служба по техническому и экспортному контролю": "102000266", "Федеральная служба по труду и занятости": "102000330", "Федеральная служба по финансовому мониторингу": "102000273", "Федеральная служба по финансовому оздоровлению и банкротству": "102000251", "Федеральная служба по финансовым рынкам": "102000252", "Федеральная служба по экологическому, технологическому и атомному надзору": "102000224", "Федеральная служба Российской Федерации по контролю за оборотом наркотиков": "102000373", "Федеральная служба Российской Федерации по контролю за оборотом наркотических средств и психотропных веществ": "102000374", "Федеральная служба специального строительства": "102000225", "Федеральная служба страхового надзора": "102000274", "Федеральная служба судебных приставов": "102000303", "Федеральная служба финансово-бюджетного надзора": "102000275", "Федеральная таможенная служба": "102000258", "Федеральная энергетическая комиссия": "102000226", "Федеральное агентство водных ресурсов": "102000339", "Федеральное агентство воздушного транспорта": "102000276", "Федеральное агентство геодезии и картографии": "102000277", "Федеральное агентство железнодорожного транспорта": "102000293", "Федеральное агентство кадастра объектов недвижимости": "102000322", "Федеральное агентство лесного хозяйства": "102000299", "Федеральное агентство морского и речного транспорта": "102000286", "Федеральное агентство научных организаций": "102376647", "Федеральное агентство по атомной энергии": "102000287", "Федеральное агентство по высокотехнологичной медицинской помощи": "102000340", "Федеральное агентство по государственным резервам": "102000327", "Федеральное агентство по делам молодежи": "102000362", "Федеральное агентство по делам национальностей": "102381438", "Федеральное агентство по делам Содружества Независимых Государств, соотечественников, проживающих за рубежом, и по международному гуманитарному сотрудничеству": "102000363", "Федеральное агентство по здравоохранению и социальному развитию": "102000295", "Федеральное агентство по информационным технологиям": "102000344", "Федеральное агентство по культуре и кинематографии": "102000325", "Федеральное агентство по науке и инновациям": "102000356", "Федеральное агентство по недропользованию": "102000346", "Федеральное агентство по образованию": "102000343", "Федеральное агентство по обустройству государственной границы": "102000351", "Федеральное агентство по печати и массовым коммуникациям": "102000278", "Федеральное агентство по поставкам вооружения, военной, специальной техники и материальных средств": "102000370", "Федеральное агентство по рыболовству": "102000288", "Федеральное агентство по строительству и жилищно-коммунальному хозяйству": "102000279", "Федеральное агентство по техническому регулированию и метрологии": "102000280", "Федеральное агентство по туризму": "102000301", "Федеральное агентство по управлению государственным имуществом": "102000359", "Федеральное агентство по управлению особыми экономическими зонами": "102000323", "Федеральное агентство по управлению федеральным имуществом": "102000267", "Федеральное агентство по физической культуре и спорту": "102000289", "Федеральное агентство по экологическому, технологическому и атомному надзору": "102000290", "Федеральное агентство по энергетике": "102000345", "Федеральное агентство правительственной связи и информации при Президенте": "102000227", "Федеральное агентство связи": "102000341", "Федеральное агентство специального строительства": "102000281", "Федеральное архивное агентство": "102000298", "Федеральное дорожное агентство": "102000329", "Федеральное казначейство": "102000291", "Федеральное космическое агентство": "102000338", "Федеральное медико-биологическое агентство": "102000300", "Федеральный горный и промышленный надзор": "102000228", "Федеральный долговой центр при Правительстве": "102000336", "Федеральный надзор по ядерной и радиационной безопасности": "102000229", "Федеральный фонд обязательного медицинского страхования": "102000230", "Федерация независимых профсоюзов": "102000084", "Фонд социального страхования": "102000231", "Фонд федерального имущества": "102000232", "Центральный банк": "102000085", "Центральный совет оборонной спортивно-технической организации": "102000259", "Центральный совет профсоюза трудящихся горно-металлургической промышленности": "102000088", "Центробанк": "102000321", "Центросоюз": "102000268", "ЦК профсоюзов работников автомобильного транспорта и дорожного хозяйства": "102000089", "ЦК Российского профсоюза работников текстильной и легкой промышленности": "102000090"}